LICENSE
README.md
__init__.py
constants.py
error.py
main.py
setup.py
controllers/__init__.py
controllers/device.py
controllers/cv/__init__.py
controllers/cv/_cv.py
controllers/cv/cv.py
controllers/tools/__init__.py
controllers/tools/image.py
controllers/tools/screen_agent.py
controllers/tools/recorder/__init__.py
controllers/tools/recorder/record_agent.py
controllers/tools/recorder/rpc_manager.py
controllers/tools/recorder/proto/__init__.py
controllers/tools/recorder/proto/scrcpy_pb2.py
controllers/tools/recorder/proto/scrcpy_pb2_grpc.py
core/__init__.py
core/constants.py
core/error_message.py
core/exception.py
core/record.py
core/report.py
core/test_case.py
core/variables.py
core/suite/__init__.py
core/suite/test_suite.py
driver/__init__.py
driver/device_test.py
driver/windows.py
log/__init__.py
log/logger.py
log/variables.py
record_actions/__init__.py
record_actions/record_action.py
record_actions/record_check.py
record_actions/record_log.py
record_actions/record_tree.py
record_actions/record_upload.py
record_actions/suggested_code.py
report/__init__.py
report/generation.py
res/prototype/native/uitest_agent_v1.1.10.so
res/prototype/native/uitest_agent_v1.1.3.so
res/prototype/native/uitest_agent_v1.1.5.so
res/prototype/native/uitest_agent_v1.1.9.x86_64_so
res/prototype/native/uitest_agent_v1.2.2.so
res/recorder/libscrcpy_server1.z.so
res/recorder/libscrcpy_server2.z.so
res/recorder/libscrcpy_server3.z.so
res/recorder/libscrcpy_server4.z.so
res/template/case.html
runner/__init__.py
runner/prepare.py
runner/test_runner.py
utils/__init__.py
utils/file_util.py
utils/img_util.py
utils/time_util.py
utils/type_utils.py
utils/util.py
xdevice_devicetest.egg-info/PKG-INFO
xdevice_devicetest.egg-info/SOURCES.txt
xdevice_devicetest.egg-info/dependency_links.txt
xdevice_devicetest.egg-info/entry_points.txt
xdevice_devicetest.egg-info/not-zip-safe
xdevice_devicetest.egg-info/requires.txt
xdevice_devicetest.egg-info/top_level.txt