Metadata-Version: 2.1
Name: xdevice-devicetest
Version: 6.0.7.210
Summary: device test runner
Home-page: UNKNOWN
License: UNKNOWN
Platform: UNKNOWN
Provides-Extra: full
License-File: LICENSE
